{
  "leagues": [
    {
      "id": "brasileirao",
      "name": "Brasileirão Série A",
      "country": "Brazil",
      "season": "2026",
      "clubs": [
        { "id": "atletico_mg", "name": "Atlético Mineiro", "short_name": "Atlético-MG", "city": "Belo Horizonte", "country": "Brazil" },
        { "id": "bahia", "name": "Bahia", "short_name": "Bahia", "city": "Salvador", "country": "Brazil" },
        { "id": "botafogo", "name": "Botafogo", "short_name": "Botafogo", "city": "Rio de Janeiro", "country": "Brazil" },
        { "id": "bragantino", "name": "Red Bull Bragantino", "short_name": "Bragantino", "city": "Bragança Paulista", "country": "Brazil" },
        { "id": "corinthians", "name": "Corinthians", "short_name": "Corinthians", "city": "São Paulo", "country": "Brazil" },
        { "id": "coritiba", "name": "Coritiba", "short_name": "Coritiba", "city": "Curitiba", "country": "Brazil" },
        { "id": "cruzeiro", "name": "Cruzeiro", "short_name": "Cruzeiro", "city": "Belo Horizonte", "country": "Brazil" },
        { "id": "flamengo", "name": "Flamengo", "short_name": "Flamengo", "city": "Rio de Janeiro", "country": "Brazil" },
        { "id": "fluminense", "name": "Fluminense", "short_name": "Fluminense", "city": "Rio de Janeiro", "country": "Brazil" },
        { "id": "gremio", "name": "Grêmio", "short_name": "Grêmio", "city": "Porto Alegre", "country": "Brazil" },
        { "id": "internacional", "name": "Internacional", "short_name": "Inter", "city": "Porto Alegre", "country": "Brazil" },
        { "id": "mirassol", "name": "Mirassol", "short_name": "Mirassol", "city": "Mirassol", "country": "Brazil" },
        { "id": "palmeiras", "name": "Palmeiras", "short_name": "Palmeiras", "city": "São Paulo", "country": "Brazil" },
        { "id": "remo", "name": "Remo", "short_name": "Remo", "city": "Belém", "country": "Brazil" },
        { "id": "santos", "name": "Santos", "short_name": "Santos", "city": "Santos", "country": "Brazil" },
        { "id": "sao_paulo", "name": "São Paulo", "short_name": "São Paulo", "city": "São Paulo", "country": "Brazil" },
        { "id": "vasco", "name": "Vasco da Gama", "short_name": "Vasco", "city": "Rio de Janeiro", "country": "Brazil" },
        { "id": "vitoria", "name": "Vitória", "short_name": "Vitória", "city": "Salvador", "country": "Brazil" },
        { "id": "athletico_pr", "name": "Athletico Paranaense", "short_name": "Athletico-PR", "city": "Curitiba", "country": "Brazil" },
        { "id": "chapecoense", "name": "Chapecoense", "short_name": "Chape", "city": "Chapecó", "country": "Brazil" }
      ]
    },
    {
      "id": "premier_league",
      "name": "Premier League",
      "country": "England",
      "season": "2025-2026",
      "clubs": [
        { "id": "arsenal", "name": "Arsenal", "short_name": "Arsenal", "city": "London", "country": "England" },
        { "id": "aston_villa", "name": "Aston Villa", "short_name": "Villa", "city": "Birmingham", "country": "England" },
        { "id": "bournemouth", "name": "Bournemouth", "short_name": "Bournemouth", "city": "Bournemouth", "country": "England" },
        { "id": "brentford", "name": "Brentford", "short_name": "Brentford", "city": "London", "country": "England" },
        { "id": "brighton", "name": "Brighton", "short_name": "Brighton", "city": "Brighton", "country": "England" },
        { "id": "chelsea", "name": "Chelsea", "short_name": "Chelsea", "city": "London", "country": "England" },
        { "id": "crystal_palace", "name": "Crystal Palace", "short_name": "Palace", "city": "London", "country": "England" },
        { "id": "everton", "name": "Everton", "short_name": "Everton", "city": "Liverpool", "country": "England" },
        { "id": "fulham", "name": "Fulham", "short_name": "Fulham", "city": "London", "country": "England" },
        { "id": "liverpool", "name": "Liverpool", "short_name": "Liverpool", "city": "Liverpool", "country": "England" },
        { "id": "luton", "name": "Luton Town", "short_name": "Luton", "city": "Luton", "country": "England" },
        { "id": "manchester_city", "name": "Manchester City", "short_name": "Man City", "city": "Manchester", "country": "England" },
        { "id": "manchester_united", "name": "Manchester United", "short_name": "Man Utd", "city": "Manchester", "country": "England" },
        { "id": "newcastle", "name": "Newcastle United", "short_name": "Newcastle", "city": "Newcastle", "country": "England" },
        { "id": "nottingham_forest", "name": "Nottingham Forest", "short_name": "Forest", "city": "Nottingham", "country": "England" },
        { "id": "sheffield_united", "name": "Sheffield United", "short_name": "Sheffield", "city": "Sheffield", "country": "England" },
        { "id": "tottenham", "name": "Tottenham", "short_name": "Spurs", "city": "London", "country": "England" },
        { "id": "west_ham", "name": "West Ham", "short_name": "West Ham", "city": "London", "country": "England" },
        { "id": "wolves", "name": "Wolverhampton", "short_name": "Wolves", "city": "Wolverhampton", "country": "England" },
        { "id": "burnley", "name": "Burnley", "short_name": "Burnley", "city": "Burnley", "country": "England" }
      ]
    },
    {
      "id": "laliga",
      "name": "La Liga",
      "country": "Spain",
      "season": "2025-2026",
      "clubs": [
        { "id": "alaves", "name": "Alavés", "short_name": "Alavés", "city": "Vitoria-Gasteiz", "country": "Spain" },
        { "id": "almeria", "name": "Almería", "short_name": "Almería", "city": "Almería", "country": "Spain" },
        { "id": "athletic_bilbao", "name": "Athletic Bilbao", "short_name": "Athletic", "city": "Bilbao", "country": "Spain" },
        { "id": "atletico_madrid", "name": "Atlético de Madrid", "short_name": "Atlético", "city": "Madrid", "country": "Spain" },
        { "id": "barcelona", "name": "FC Barcelona", "short_name": "Barcelona", "city": "Barcelona", "country": "Spain" },
        { "id": "cadiz", "name": "Cádiz", "short_name": "Cádiz", "city": "Cádiz", "country": "Spain" },
        { "id": "celta_vigo", "name": "Celta de Vigo", "short_name": "Celta", "city": "Vigo", "country": "Spain" },
        { "id": "getafe", "name": "Getafe", "short_name": "Getafe", "city": "Getafe", "country": "Spain" },
        { "id": "girona", "name": "Girona", "short_name": "Girona", "city": "Girona", "country": "Spain" },
        { "id": "granada", "name": "Granada", "short_name": "Granada", "city": "Granada", "country": "Spain" },
        { "id": "las_palmas", "name": "Las Palmas", "short_name": "Las Palmas", "city": "Las Palmas", "country": "Spain" },
        { "id": "mallorca", "name": "Mallorca", "short_name": "Mallorca", "city": "Palma", "country": "Spain" },
        { "id": "osasuna", "name": "Osasuna", "short_name": "Osasuna", "city": "Pamplona", "country": "Spain" },
        { "id": "rayo_vallecano", "name": "Rayo Vallecano", "short_name": "Rayo", "city": "Madrid", "country": "Spain" },
        { "id": "real_betis", "name": "Real Betis", "short_name": "Betis", "city": "Seville", "country": "Spain" },
        { "id": "real_madrid", "name": "Real Madrid", "short_name": "Real Madrid", "city": "Madrid", "country": "Spain" },
        { "id": "real_sociedad", "name": "Real Sociedad", "short_name": "Sociedad", "city": "San Sebastián", "country": "Spain" },
        { "id": "sevilla", "name": "Sevilla", "short_name": "Sevilla", "city": "Seville", "country": "Spain" },
        { "id": "valencia", "name": "Valencia", "short_name": "Valencia", "city": "Valencia", "country": "Spain" },
        { "id": "villarreal", "name": "Villarreal", "short_name": "Villarreal", "city": "Villarreal", "country": "Spain" }
      ]
    },
    {
      "id": "serie_a",
      "name": "Serie A",
      "country": "Italy",
      "season": "2025-2026",
      "clubs": [
        { "id": "atalanta", "name": "Atalanta", "short_name": "Atalanta", "city": "Bergamo", "country": "Italy" },
        { "id": "bologna", "name": "Bologna", "short_name": "Bologna", "city": "Bologna", "country": "Italy" },
        { "id": "cagliari", "name": "Cagliari", "short_name": "Cagliari", "city": "Cagliari", "country": "Italy" },
        { "id": "empoli", "name": "Empoli", "short_name": "Empoli", "city": "Empoli", "country": "Italy" },
        { "id": "fiorentina", "name": "Fiorentina", "short_name": "Fiorentina", "city": "Florence", "country": "Italy" },
        { "id": "frosinone", "name": "Frosinone", "short_name": "Frosinone", "city": "Frosinone", "country": "Italy" },
        { "id": "genoa", "name": "Genoa", "short_name": "Genoa", "city": "Genoa", "country": "Italy" },
        { "id": "inter_milan", "name": "Inter Milan", "short_name": "Inter", "city": "Milan", "country": "Italy" },
        { "id": "juventus", "name": "Juventus", "short_name": "Juve", "city": "Turin", "country": "Italy" },
        { "id": "lazio", "name": "Lazio", "short_name": "Lazio", "city": "Rome", "country": "Italy" },
        { "id": "lecce", "name": "Lecce", "short_name": "Lecce", "city": "Lecce", "country": "Italy" },
        { "id": "ac_milan", "name": "AC Milan", "short_name": "Milan", "city": "Milan", "country": "Italy" },
        { "id": "monza", "name": "Monza", "short_name": "Monza", "city": "Monza", "country": "Italy" },
        { "id": "napoli", "name": "Napoli", "short_name": "Napoli", "city": "Naples", "country": "Italy" },
        { "id": "roma", "name": "AS Roma", "short_name": "Roma", "city": "Rome", "country": "Italy" },
        { "id": "salernitana", "name": "Salernitana", "short_name": "Salernitana", "city": "Salerno", "country": "Italy" },
        { "id": "sassuolo", "name": "Sassuolo", "short_name": "Sassuolo", "city": "Sassuolo", "country": "Italy" },
        { "id": "torino", "name": "Torino", "short_name": "Torino", "city": "Turin", "country": "Italy" },
        { "id": "udinese", "name": "Udinese", "short_name": "Udinese", "city": "Udine", "country": "Italy" },
        { "id": "verona", "name": "Hellas Verona", "short_name": "Verona", "city": "Verona", "country": "Italy" }
      ]
    },
    {
      "id": "bundesliga",
      "name": "Bundesliga",
      "country": "Germany",
      "season": "2025-2026",
      "clubs": [
        { "id": "augsburg", "name": "Augsburg", "short_name": "Augsburg", "city": "Augsburg", "country": "Germany" },
        { "id": "bayer_leverkusen", "name": "Bayer Leverkusen", "short_name": "Leverkusen", "city": "Leverkusen", "country": "Germany" },
        { "id": "bayern_munich", "name": "Bayern Munich", "short_name": "Bayern", "city": "Munich", "country": "Germany" },
        { "id": "bochum", "name": "Bochum", "short_name": "Bochum", "city": "Bochum", "country": "Germany" },
        { "id": "borussia_dortmund", "name": "Borussia Dortmund", "short_name": "Dortmund", "city": "Dortmund", "country": "Germany" },
        { "id": "borussia_monchengladbach", "name": "Borussia Mönchengladbach", "short_name": "Gladbach", "city": "Mönchengladbach", "country": "Germany" },
        { "id": "darmstadt", "name": "Darmstadt", "short_name": "Darmstadt", "city": "Darmstadt", "country": "Germany" },
        { "id": "eintracht_frankfurt", "name": "Eintracht Frankfurt", "short_name": "Frankfurt", "city": "Frankfurt", "country": "Germany" },
        { "id": "freiburg", "name": "Freiburg", "short_name": "Freiburg", "city": "Freiburg", "country": "Germany" },
        { "id": "heidenheim", "name": "Heidenheim", "short_name": "Heidenheim", "city": "Heidenheim", "country": "Germany" },
        { "id": "hoffenheim", "name": "Hoffenheim", "short_name": "Hoffenheim", "city": "Sinsheim", "country": "Germany" },
        { "id": "koln", "name": "Köln", "short_name": "Köln", "city": "Cologne", "country": "Germany" },
        { "id": "mainz", "name": "Mainz 05", "short_name": "Mainz", "city": "Mainz", "country": "Germany" },
        { "id": "rb_leipzig", "name": "RB Leipzig", "short_name": "Leipzig", "city": "Leipzig", "country": "Germany" },
        { "id": "stuttgart", "name": "Stuttgart", "short_name": "Stuttgart", "city": "Stuttgart", "country": "Germany" },
        { "id": "union_berlin", "name": "Union Berlin", "short_name": "Union", "city": "Berlin", "country": "Germany" },
        { "id": "werder_bremen", "name": "Werder Bremen", "short_name": "Bremen", "city": "Bremen", "country": "Germany" },
        { "id": "wolfsburg", "name": "Wolfsburg", "short_name": "Wolfsburg", "city": "Wolfsburg", "country": "Germany" }
      ]
    },
    {
      "id": "argentina_primera",
      "name": "Liga Profesional Argentina",
      "country": "Argentina",
      "season": "2025-2026",
      "clubs": [
        { "id": "argentinos_juniors", "name": "Argentinos Juniors", "short_name": "Argentinos", "city": "Buenos Aires", "country": "Argentina" },
        { "id": "arsenal_sarandi", "name": "Arsenal de Sarandí", "short_name": "Arsenal", "city": "Sarandí", "country": "Argentina" },
        { "id": "atletico_tucuman", "name": "Atlético Tucumán", "short_name": "Tucumán", "city": "San Miguel de Tucumán", "country": "Argentina" },
        { "id": "banfield", "name": "Banfield", "short_name": "Banfield", "city": "Banfield", "country": "Argentina" },
        { "id": "barracas_central", "name": "Barracas Central", "short_name": "Barracas", "city": "Buenos Aires", "country": "Argentina" },
        { "id": "belgrano", "name": "Belgrano", "short_name": "Belgrano", "city": "Córdoba", "country": "Argentina" },
        { "id": "boca_juniors", "name": "Boca Juniors", "short_name": "Boca", "city": "Buenos Aires", "country": "Argentina" },
        { "id": "central_cordoba", "name": "Central Córdoba", "short_name": "Central Córdoba", "city": "Santiago del Estero", "country": "Argentina" },
        { "id": "colon", "name": "Colón", "short_name": "Colón", "city": "Santa Fe", "country": "Argentina" },
        { "id": "defensa_justicia", "name": "Defensa y Justicia", "short_name": "Defensa", "city": "Florencio Varela", "country": "Argentina" },
        { "id": "estudiantes", "name": "Estudiantes", "short_name": "Estudiantes", "city": "La Plata", "country": "Argentina" },
        { "id": "gimnasia_lp", "name": "Gimnasia La Plata", "short_name": "Gimnasia", "city": "La Plata", "country": "Argentina" },
        { "id": "godoy_cruz", "name": "Godoy Cruz", "short_name": "Godoy Cruz", "city": "Mendoza", "country": "Argentina" },
        { "id": "huracan", "name": "Huracán", "short_name": "Huracán", "city": "Buenos Aires", "country": "Argentina" },
        { "id": "independiente", "name": "Independiente", "short_name": "Independiente", "city": "Avellaneda", "country": "Argentina" },
        { "id": "instituto", "name": "Instituto", "short_name": "Instituto", "city": "Córdoba", "country": "Argentina" },
        { "id": "lanus", "name": "Lanús", "short_name": "Lanús", "city": "Lanús", "country": "Argentina" },
        { "id": "newells_old_boys", "name": "Newell's Old Boys", "short_name": "Newell's", "city": "Rosario", "country": "Argentina" },
        { "id": "platense", "name": "Platense", "short_name": "Platense", "city": "Vicente López", "country": "Argentina" },
        { "id": "racing", "name": "Racing Club", "short_name": "Racing", "city": "Avellaneda", "country": "Argentina" },
        { "id": "river_plate", "name": "River Plate", "short_name": "River", "city": "Buenos Aires", "country": "Argentina" },
        { "id": "rosario_central", "name": "Rosario Central", "short_name": "Rosario", "city": "Rosario", "country": "Argentina" },
        { "id": "san_lorenzo", "name": "San Lorenzo", "short_name": "San Lorenzo", "city": "Buenos Aires", "country": "Argentina" },
        { "id": "sarmiento", "name": "Sarmiento", "short_name": "Sarmiento", "city": "Junín", "country": "Argentina" },
        { "id": "talleres", "name": "Talleres", "short_name": "Talleres", "city": "Córdoba", "country": "Argentina" },
        { "id": "tigre", "name": "Tigre", "short_name": "Tigre", "city": "Victoria", "country": "Argentina" },
        { "id": "union", "name": "Unión", "short_name": "Unión", "city": "Santa Fe", "country": "Argentina" },
        { "id": "velez", "name": "Vélez Sarsfield", "short_name": "Vélez", "city": "Buenos Aires", "country": "Argentina" }
      ]
    },
    {
      "id": "uruguay_primera",
      "name": "Primera División Uruguaya",
      "country": "Uruguay",
      "season": "2025",
      "clubs": [
        { "id": "penarol", "name": "Peñarol", "short_name": "Peñarol", "city": "Montevideo", "country": "Uruguay" },
        { "id": "nacional", "name": "Nacional", "short_name": "Nacional", "city": "Montevideo", "country": "Uruguay" },
        { "id": "defensor", "name": "Defensor Sporting", "short_name": "Defensor", "city": "Montevideo", "country": "Uruguay" },
        { "id": "danubio", "name": "Danubio", "short_name": "Danubio", "city": "Montevideo", "country": "Uruguay" },
        { "id": "liverpool_uru", "name": "Liverpool Montevideo", "short_name": "Liverpool", "city": "Montevideo", "country": "Uruguay" },
        { "id": "river_plate_uru", "name": "River Plate Montevideo", "short_name": "River", "city": "Montevideo", "country": "Uruguay" },
        { "id": "wanderers", "name": "Montevideo Wanderers", "short_name": "Wanderers", "city": "Montevideo", "country": "Uruguay" },
        { "id": "cerro", "name": "Cerro", "short_name": "Cerro", "city": "Montevideo", "country": "Uruguay" },
        { "id": "cerro_largo", "name": "Cerro Largo", "short_name": "Cerro Largo", "city": "Melo", "country": "Uruguay" },
        { "id": "plaza_colonia", "name": "Plaza Colonia", "short_name": "Plaza", "city": "Colonia", "country": "Uruguay" },
        { "id": "boston_river", "name": "Boston River", "short_name": "Boston River", "city": "Montevideo", "country": "Uruguay" },
        { "id": "la_luz", "name": "La Luz", "short_name": "La Luz", "city": "Montevideo", "country": "Uruguay" },
        { "id": "deportivo_maldonado", "name": "Deportivo Maldonado", "short_name": "Maldonado", "city": "Maldonado", "country": "Uruguay" },
        { "id": "fenix", "name": "Fénix", "short_name": "Fénix", "city": "Montevideo", "country": "Uruguay" },
        { "id": "rentistas", "name": "Rentistas", "short_name": "Rentistas", "city": "Montevideo", "country": "Uruguay" },
        { "id": "torque", "name": "Montevideo City Torque", "short_name": "Torque", "city": "Montevideo", "country": "Uruguay" }
      ]
    },
    {
      "id": "paraguay_primera",
      "name": "Primera División Paraguay",
      "country": "Paraguay",
      "season": "2025",
      "clubs": [
        { "id": "olimpia", "name": "Olimpia", "short_name": "Olimpia", "city": "Asunción", "country": "Paraguay" },
        { "id": "cerro_porteno", "name": "Cerro Porteño", "short_name": "Cerro", "city": "Asunción", "country": "Paraguay" },
        { "id": "libertad", "name": "Libertad", "short_name": "Libertad", "city": "Asunción", "country": "Paraguay" },
        { "id": "guarani", "name": "Guaraní", "short_name": "Guaraní", "city": "Asunción", "country": "Paraguay" },
        { "id": "nacional_py", "name": "Nacional", "short_name": "Nacional", "city": "Asunción", "country": "Paraguay" },
        { "id": "sportivo_luqueno", "name": "Sportivo Luqueño", "short_name": "Luqueño", "city": "Luque", "country": "Paraguay" },
        { "id": "general_caballero", "name": "General Caballero", "short_name": "Caballero", "city": "Juan León Mallorquín", "country": "Paraguay" },
        { "id": "resistencia", "name": "Resistencia", "short_name": "Resistencia", "city": "Asunción", "country": "Paraguay" },
        { "id": "trini", "name": "Sportivo Trinidense", "short_name": "Trinidense", "city": "Asunción", "country": "Paraguay" },
        { "id": "tacuary", "name": "Tacuary", "short_name": "Tacuary", "city": "Asunción", "country": "Paraguay" },
        { "id": "2_de_mayo", "name": "2 de Mayo", "short_name": "2 de Mayo", "city": "Pedro Juan Caballero", "country": "Paraguay" },
        { "id": "sol_america", "name": "Sol de América", "short_name": "Sol", "city": "Asunción", "country": "Paraguay" }
      ]
    },
    {
      "id": "mls",
      "name": "Major League Soccer",
      "country": "USA",
      "season": "2025",
      "clubs": [
        { "id": "inter_miami", "name": "Inter Miami", "short_name": "Miami", "city": "Miami", "country": "USA" },
        { "id": "la_galaxy", "name": "LA Galaxy", "short_name": "Galaxy", "city": "Los Angeles", "country": "USA" },
        { "id": "lafc", "name": "Los Angeles FC", "short_name": "LAFC", "city": "Los Angeles", "country": "USA" },
        { "id": "new_york_city", "name": "New York City FC", "short_name": "NYCFC", "city": "New York", "country": "USA" },
        { "id": "new_york_red_bulls", "name": "New York Red Bulls", "short_name": "Red Bulls", "city": "New York", "country": "USA" },
        { "id": "atlanta_united", "name": "Atlanta United", "short_name": "Atlanta", "city": "Atlanta", "country": "USA" },
        { "id": "seattle_sounders", "name": "Seattle Sounders", "short_name": "Seattle", "city": "Seattle", "country": "USA" },
        { "id": "orlando_city", "name": "Orlando City", "short_name": "Orlando", "city": "Orlando", "country": "USA" },
        { "id": "chicago_fire", "name": "Chicago Fire", "short_name": "Chicago", "city": "Chicago", "country": "USA" },
        { "id": "dc_united", "name": "DC United", "short_name": "DC", "city": "Washington", "country": "USA" },
        { "id": "houston_dynamo", "name": "Houston Dynamo", "short_name": "Houston", "city": "Houston", "country": "USA" },
        { "id": "toronto_fc", "name": "Toronto FC", "short_name": "Toronto", "city": "Toronto", "country": "Canada" },
        { "id": "vancouver_whitecaps", "name": "Vancouver Whitecaps", "short_name": "Vancouver", "city": "Vancouver", "country": "Canada" },
        { "id": "cf_montreal", "name": "CF Montréal", "short_name": "Montréal", "city": "Montreal", "country": "Canada" }
      ]
    }
  ]
}
